coding_agent/__init__.py
coding_agent/cli.py
coding_agent/types/__init__.py
coding_agent/types/gitea.py
coding_agent/types/headers.py
codexagent-0.1.0.dist-info/METADATA
codexagent-0.1.0.dist-info/WHEEL
codexagent-0.1.0.dist-info/entry_points.txt
codexagent-0.1.0.dist-info/licenses/LICENSE
codexagent-0.1.0.dist-info/RECORD
