Metadata-Version: 2.4
Name: CodexAgent
Version: 0.1.0
Summary: Repository template for Python projects
Project-URL: Homepage, https://github.com/Mai0313/CodingAgent
Project-URL: Repository, https://github.com/Mai0313/CodingAgent
Author-email: Wei <mai@mai0313.com>
License: MIT
License-File: LICENSE
Requires-Python: >=3.10
Requires-Dist: fastapi[standard]>=0.116.1
Requires-Dist: pydantic>=2.11.7
Requires-Dist: rich>=14.1.0
